mr_recv_coil_match_networks/__init__.py
mr_recv_coil_match_networks/preamp_decoupling.py
mr_recv_coil_match_networks/topology.py
mr_recv_coil_match_networks-2.0.0.dist-info/LICENSE
mr_recv_coil_match_networks-2.0.0.dist-info/METADATA
mr_recv_coil_match_networks-2.0.0.dist-info/WHEEL
mr_recv_coil_match_networks-2.0.0.dist-info/top_level.txt
mr_recv_coil_match_networks-2.0.0.dist-info/RECORD
