Metadata-Version: 2.1
Name: mr-recv-coil-match-networks
Version: 2.0.0
Summary: Models MRI receive coil matching networks
Author-email: Rasmus Jepsen <rasale@dtu.dk>
License: LGPL-2.1-or-later
Project-URL: Homepage, https://github.com/dtudk/mr-recv-coil-match-networks
Project-URL: Bug Tracker, https://github.com/dtudk/mr-recv-coil-match-networks/issues
Classifier: Programming Language :: Python :: 3
Classifier: Operating System :: OS Independent
Requires-Python: >=3.10
License-File: LICENSE
Requires-Dist: lcapy>=1.15
Requires-Dist: numpy>=1.24.3
Requires-Dist: sympy>=1.12
Requires-Dist: scikit_rf>=0.31.0
Requires-Dist: lc_power_match_baluns~=2.0.0
Requires-Dist: multimethod>=1.11.2
